awsipranges/__init__.py
awsipranges/config.py
awsipranges/data_loading.py
awsipranges/exceptions.py
awsipranges/models/__init__.py
awsipranges/models/awsipprefix.py
awsipranges/models/awsipprefixes.py
awsipranges/utils.py
awsipranges-0.3.1.dist-info/LICENSE
awsipranges-0.3.1.dist-info/WHEEL
awsipranges-0.3.1.dist-info/METADATA
awsipranges-0.3.1.dist-info/RECORD
