Metadata-Version: 2.1
Name: awsipranges
Version: 0.3.1
Summary: Work with the AWS IP address ranges in native Python.
Home-page: https://aws-samples.github.io/awsipranges/
License: Apache-2.0
Keywords: AWS,IP,ranges,addresses
Author: Chris Lunsford
Author-email: cmluns@amazon.com
Requires-Python: >=3.7,<4.0
Classifier: Intended Audience :: Developers
Classifier: Intended Audience :: Information Technology
Classifier: Intended Audience :: System Administrators
Classifier: Intended Audience :: Telecommunications Industry
Classifier: License :: OSI Approved :: Apache Software License
Classifier: Natural Language :: English
Classifier: Operating System :: OS Independent
Classifier: Programming Language :: Python :: 3
Classifier: Programming Language :: Python :: 3.7
Classifier: Programming Language :: Python :: 3.8
Classifier: Programming Language :: Python :: 3.9
Classifier: Topic :: Internet
Classifier: Topic :: Software Development :: Libraries :: Python Modules
Classifier: Topic :: System :: Networking
Classifier: Topic :: System :: Systems Administration
Project-URL: Documentation, https://aws-samples.github.io/awsipranges/
Project-URL: Repository, https://github.com/aws-samples/awsipranges
